univlm/Model.py
univlm/Model_utils.py
univlm/__init__.py
univlm/scripts/__init__.py
univlm/scripts/download_src.sh
univlm/scripts/install_and_test.py
univlm/scripts/install_and_test.sh
univlm/scripts/testing.py
univlm-1.0.2.dist-info/LICENSE
univlm-1.0.2.dist-info/METADATA
univlm-1.0.2.dist-info/WHEEL
univlm-1.0.2.dist-info/entry_points.txt
univlm-1.0.2.dist-info/top_level.txt
univlm-1.0.2.dist-info/RECORD
