Metadata-Version: 2.2
Name: univlm
Version: 1.0.2
Summary: Unified wrapper for HF, VLLM and other models
Author-email: Tyagi <siddhant.tyagizx@gmail.com>, Singh <sk.singharyan99@gmail.com>
License: Apache License 2.0
Classifier: Programming Language :: Python :: 3
Classifier: Operating System :: POSIX :: Linux
Classifier: License :: OSI Approved :: Apache Software License
Requires-Python: >=3.10
License-File: LICENSE
Requires-Dist: huggingface_hub>=0.20.2
Requires-Dist: transformers>=4.35.0
Requires-Dist: diffusers>=0.24.0
Requires-Dist: fuzzywuzzy>=0.18.0
Requires-Dist: vllm>=0.2.0
